snappy/__init__.py
snappy/cli.py
snappy_pyr-0.1.0.dist-info/METADATA
snappy_pyr-0.1.0.dist-info/WHEEL
snappy_pyr-0.1.0.dist-info/entry_points.txt
snappy_pyr-0.1.0.dist-info/top_level.txt
snappy_pyr-0.1.0.dist-info/RECORD
