Metadata-Version: 2.4
Name: snappy-pyr
Version: 0.1.0
Summary: Run python files faster with pyr
Author-email: Ganu Reddy <ganureddy54@gmail.com>
License: MIT
Requires-Python: >=3.7
